{
  "total_unique_words": 35000,
  "total_tokens": 506769,
  "output_csv": "/home/r1ppa/Desktop/New Folder/hyperlex demo/server/data/uzbek_35k/uzbek_35k_real_words.csv",
  "sources": [
    {
      "name": "local_corpora",
      "tokens": 252315,
      "accepted": 0
    }
  ],
  "sample": [
    "va",
    "bilan",
    "ham",
    "bu",
    "uchun",
    "bir",
    "shu",
    "bo'yicha",
    "tomonidan",
    "o'zbekiston",
    "tashkil",
    "davlat",
    "ushbu",
    "olib",
    "ming",
    "o'z",
    "bo'lgan",
    "ta",
    "har",
    "bo'lib",
    "amalga",
    "hamda",
    "yangi",
    "esa",
    "qilish",
    "joriy",
    "ish",
    "mazkur",
    "ishlab",
    "nafar",
    "barcha",
    "ta'lim",
    "edi",
    "eng",
    "mumkin",
    "shuningdek",
    "etish",
    "uning",
    "bor",
    "respublikasi",
    "yil",
    "orqali",
    "boshqa",
    "xalqaro",
    "qabul",
    "deb",
    "ularning",
    "ishlar",
    "million",
    "olish",
    "katta",
    "yoki",
    "yana",
    "ko'ra",
    "emas",
    "bugungi",
    "etilgan",
    "toshkent",
    "oliy",
    "kabi",
    "muhim",
    "kerak",
    "ayni",
    "ko'p",
    "o'tgan",
    "qarshi",
    "kuni",
    "xizmat",
    "ijtimoiy",
    "etildi",
    "qilib",
    "shunday",
    "haqida",
    "ular",
    "ikki",
    "koronavirus",
    "-yil",
    "asosida",
    "bo'ladi",
    "bugun",
    "bo'ldi",
    "ega",
    "kunda",
    "milliy",
    "bosh",
    "ishlari",
    "yoshlar",
    "alohida",
    "davomida",
    "viloyat",
    "qanday",
    "bundan",
    "qilindi",
    "aholi",
    "mavjud",
    "holda",
    "tuman",
    "ma'lum",
    "kelib",
    "oshirish"
  ]
}